django_namek/__init__.py
django_namek/abstract.py
django_namek/actions.py
django_namek/admin.py
django_namek/constants.py
django_namek/exceptions.py
django_namek/forms.py
django_namek/mail.py
django_namek/models.py
django_namek/session.py
django_namek/urls.py
django_namek/utils.py
django_namek/views.py
django_namek/migrations/0001_initial.py
django_namek/migrations/__init__.py
django_namek/templates/django_namek/base.html
django_namek/templates/django_namek/index.html
django_namek/templates/django_namek/results.html
django_namek/templates/django_namek/validation.html
django_namek/templates/django_namek/forms/form.html
django_namek/templates/django_namek/forms/form_display.html
django_namek/templates/django_namek/mails/mail.html
django_namek/templates/django_namek/mails/validation.html
django_namek/tests/__init__.py
django_namek/tests/client.py
django_namek/tests/faker.py
django_namek/tests/test_case.py
django_namek/tests/events/__init__.py
django_namek/tests/events/_event.py
django_namek/tests/events/workflow.py
tests/__init__.py
tests/actions.py
tests/forms.py
tests/views.py
tests/management/__init__.py
tests/management/commands/__init__.py
tests/management/commands/init.py
django_namek-0.0.3.dist-info/LICENSE
django_namek-0.0.3.dist-info/METADATA
django_namek-0.0.3.dist-info/WHEEL
django_namek-0.0.3.dist-info/top_level.txt
django_namek-0.0.3.dist-info/RECORD
