Metadata-Version: 2.1
Name: django-namek
Version: 0.0.3
Summary: Django app for forms chaining with some features
Home-page: https://github.com/Aleksi44/django-namek
Author: Alexis Le Baron
Author-email: hello@snoweb.fr
License: GPL-3.0
Keywords: django forms session namek
Platform: linux
Classifier: Environment :: Web Environment
Classifier: Intended Audience :: Developers
Classifier: Programming Language :: Python
Classifier: Programming Language :: Python :: 3
Classifier: Programming Language :: Python :: 3.6
Classifier: Programming Language :: Python :: 3.7
Classifier: Programming Language :: Python :: 3.8
Classifier: Operating System :: OS Independent
Classifier: Topic :: Software Development
Requires-Dist: django (>=3.1.1)
Requires-Dist: selenium (>=3.141.0)
Requires-Dist: pyvirtualdisplay (>=0.2.5)
Requires-Dist: Faker (>=4.14.0)
Requires-Dist: webdriver-manager (>=3.2.2)
